strct/__init__.py
strct/main.py
strct/commands/__init__.py
strct/commands/add.py
strct/commands/copy.py
strct/commands/create_structure.py
strct/commands/delete.py
strct/commands/help.py
strct/commands/list.py
strct/commands/version.py
strct/commands/git/__init__.py
strct/commands/git/git_operations.py
strct/commands/git/handler.py
strct/utilities/__init__.py
strct/utilities/general.py
strct_tool-0.4.9.dist-info/METADATA
strct_tool-0.4.9.dist-info/WHEEL
strct_tool-0.4.9.dist-info/entry_points.txt
strct_tool-0.4.9.dist-info/top_level.txt
strct_tool-0.4.9.dist-info/RECORD
